
[{"content":" Here you can find a list of all blog posts I\u0026rsquo;ve written ","date":"1 June 2025","externalUrl":null,"permalink":"/posts/","section":"Blog Posts","summary":"","title":"Blog Posts","type":"posts"},{"content":"","date":"1 June 2025","externalUrl":null,"permalink":"/","section":"Welcome to my personal space on the Internet! 🎉","summary":"","title":"Welcome to my personal space on the Internet! 🎉","type":"page"},{"content":"","date":"14 August 2020","externalUrl":null,"permalink":"/tags/java/","section":"Tags","summary":"","title":"Java","type":"tags"},{"content":"","date":"14 August 2020","externalUrl":null,"permalink":"/tags/opensource/","section":"Tags","summary":"","title":"Opensource","type":"tags"},{"content":" Here you can find a list of (open source) projects I created or contributed to :heart_eyes: ","date":"14 August 2020","externalUrl":null,"permalink":"/projects/","section":"Projects","summary":"","title":"Projects","type":"projects"},{"content":"","date":"14 August 2020","externalUrl":null,"permalink":"/tags/","section":"Tags","summary":"","title":"Tags","type":"tags"},{"content":"The Tus Java Server project.\n","date":"14 August 2020","externalUrl":null,"permalink":"/projects/tus-java-server/","section":"Projects","summary":"tus-java-server summary TODO","title":"tus-java-server","type":"projects"},{"content":"This is me! :-)\n","externalUrl":null,"permalink":"/about/","section":"Welcome to my personal space on the Internet! 🎉","summary":"","title":"About Me","type":"page"},{"content":"","externalUrl":null,"permalink":"/categories/","section":"Categories","summary":"","title":"Categories","type":"categories"},{"content":"TODO\n","externalUrl":null,"permalink":"/privacy/","section":"Welcome to my personal space on the Internet! 🎉","summary":"","title":"Privacy Policy","type":"page"}]